{
  "openapi": "3.0.3",
  "info": {
    "title": "My API",
    "description": "",
    "version": "1.0",
    "contact": {}
  },
  "servers": [],
  "paths": {
    "/api/user/{id}": {
      "get": {
        "operationId": "AppController_getUser",
        "parameters": [
          {
            "name": "id",
            "required": true,
            "in": "path",
            "schema": {
              "type": "number"
            }
          }
        ],
        "responses": {
          "200": {
            "description": ""
          }
        },
        "tags": [
          "App"
        ]
      }
    },
    "/api/login": {
      "post": {
        "operationId": "AppController_login",
        "parameters": [],
        "requestBody": {
          "required": true,
          "content": {
            "application/json": {
              "schema": {
                "$ref": "#/components/schemas/LoginRequest"
              }
            }
          }
        },
        "responses": {
          "200": {
            "description": "Login successful",
            "content": {
              "application/json": {
                "schema": {
                  "$ref": "#/components/schemas/LoginResponse"
                }
              }
            }
          }
        },
        "tags": [
          "App"
        ]
      }
    },
    "/api/product/{productId}": {
      "get": {
        "operationId": "ProductController_getProduct",
        "parameters": [
          {
            "name": "productId",
            "required": true,
            "in": "path",
            "schema": {
              "type": "string"
            }
          }
        ],
        "responses": {
          "200": {
            "description": "Product fetched successfully",
            "content": {
              "application/json": {
                "schema": {
                  "$ref": "#/components/schemas/Product"
                }
              }
            }
          }
        },
        "tags": [
          "Product"
        ]
      }
    }
  },
  "components": {
    "schemas": {
      "LoginRequest": {
        "type": "object",
        "properties": {
          "username": {
            "type": "string",
            "description": "The username of the user"
          },
          "password": {
            "type": "string",
            "description": "The password of the user"
          }
        },
        "required": [
          "username",
          "password"
        ]
      },
      "LoginResponse": {
        "type": "object",
        "properties": {
          "jwt": {
            "type": "string"
          }
        },
        "required": [
          "jwt"
        ]
      },
      "Product": {
        "type": "object",
        "properties": {
          "id": {
            "type": "string"
          },
          "name": {
            "type": "string"
          },
          "price": {
            "type": "number"
          }
        },
        "required": [
          "id",
          "name",
          "price"
        ]
      }
    }
  }
}